{"1": {"title": "ANA\u0301LISIS | El Bernabe\u0301u dejo\u0301 de creer: el Real Madrid, ante su mayor fractura interna en an\u0303os", "imgUrl": "https://imgresizer.eurosport.com/unsafe/2400x1260/filters:format(jpeg)/origin-imgresizer.eurosport.com/2026/01/17/image-937b2cc6-e777-4f69-af68-ade09cc79ab8-85-2560-1440.jpeg", "tags": ["football", "la liga 2025/2026"], "link": "https://www.eurosport.es/futbol/la-liga/2025-2026/real-madrid-mayor-fractura-interna-anos-pitos-abucheos-panolada-santiago-bernabeu_sto23260051/story.shtml", "date": "2026-01-17 17:13:07", "sentiment_score": -0.6105208843946457, "publisher": "eurosport_es"}, "2": {"title": "ANA\u0301LISIS | El Bernabe\u0301u dejo\u0301 de creer: el Real Madrid, ante su mayor fractura interna en an\u0303os", "imgUrl": "https://imgresizer.eurosport.com/unsafe/2400x1260/filters:format(jpeg)/origin-imgresizer.eurosport.com/2026/01/17/image-937b2cc6-e777-4f69-af68-ade09cc79ab8-85-2560-1440.jpeg", "tags": ["la liga 2025/2026", "football"], "link": "https://espanol.eurosport.com/futbol/la-liga/2025-2026/real-madrid-mayor-fractura-interna-anos-pitos-abucheos-panolada-santiago-bernabeu_sto23260051/story.shtml", "date": "2026-01-17 17:13:07", "sentiment_score": -0.6105208843946457, "publisher": "eurosport_espanol"}, "3": {"title": "Alquilar en 2026: ma\u0301s caro, menos pisos y fuera del alcance de muchas familias", "imgUrl": "https://fotografias.antena3.com/clipping/cmsimages02/2026/01/17/CB83F304-0779-4A18-8BAC-543ACEDDDB98/alquilar-2026-mas-caro-menos-pisos-fuera-alcance-muchas-familias_70.jpg?crop=1920%2C1080%2Cx0%2Cy0&format=webply&height=270&optimize=high&width=480", "tags": ["econom\u00eda", "antena 3 noticias"], "link": "https://www.antena3.com/noticias/economia/alquilar-2026-mas-caro-menos-pisos-fuera-alcance-muchas-familias_20260117696bb3e35b0f0226996ad727.html", "date": "2026-01-17 17:06:42", "sentiment_score": -0.805440915748477, "publisher": "antena3"}, "4": {"title": "Manolo Lama: \"Escuchar 'Florentino, dimisio\u0301n' es una queja una\u0301nime de la gestio\u0301n que el presidente del Real Madrid esta\u0301 haciendo con el equipo\"", "imgUrl": "https://imagenes.cope.es/files/webp_425_238/uploads/2026/01/17/696bbd3bae55a.png", "tags": ["tiempo de juego"], "link": "https://www.cope.es/programas/tiempo-de-juego/noticias/manolo-lama-escuchar-florentino-dimision-queja-unanime-gestion-presidente-real-madrid-haciendo-equipo-20260117_3288918.html", "date": "2026-01-17 17:06:11", "sentiment_score": -0.006841093301773071, "publisher": "cope_es"}, "5": {"title": "La estadi\u0301stica que explica la paliza del Real Madrid al Barc\u0327a de basket en la Euroliga: tres sen\u0303alados", "imgUrl": "https://a2.elespanol.com/cronicaglobal/2026/01/16/culemania/secciones/1003742724035_15611058_1706x960.jpg", "tags": ["fcb basket", "secciones", "xavi pascual", "willy hernang\u00f3mez"], "link": "https://cronicaglobal.elespanol.com/culemania/secciones/20260117/estadistica-explica-real-madrid-barca-euroliga-senalados/1003742724133_0.html", "date": "2026-01-17 17:05:15", "sentiment_score": -0.1529516875743866, "publisher": "cronicaglobal_elespanol"}, "6": {"title": "El papel de la princesa Leonor y la infanta Sofi\u0301a, la presencia de otras dinasti\u0301as reales y el apoyo de Felipe VI: la ceremonia en recuerdo a Irene de Grecia, en ima\u0301genes", "imgUrl": "https://images.ecestaticos.com/fI1Pwqrww9s5fGZdwFoNpcq9JZI=/0x0:800x600/1600x900/filters:fill(white):format(jpg)/f.elconfidencial.com%2Foriginal%2F167%2Fafb%2Fa7c%2F167afba7c59d5eefd1ee6dae1127b93e.jpg", "tags": ["lifestyle", "top"], "link": "https://www.vanitatis.elconfidencial.com/casas-reales/2026-01-17/ceremonia-irene-de-grecia-imagenes-papel-leonor_4285864/", "date": "2026-01-17 17:01:00", "sentiment_score": -0.36638250574469566, "publisher": "elconfidencial"}, "7": {"title": "La ceremonia en honor a Irene de Grecia, desde dentro: de las fotos que revelan el lenguaje no verbal de la familia real a la mu\u0301sica escogida por Sofi\u0301a", "imgUrl": "https://images.ecestaticos.com/BHxQKzXjyOj16xJYRHapGM35wdo=/0x0:1920x1283/1600x900/filters:fill(white):format(jpg)/f.elconfidencial.com%2Foriginal%2Fabb%2Ff7e%2F598%2Fabbf7e598dec7da122249e0e216dea2b.jpg", "tags": ["top"], "link": "https://www.vanitatis.elconfidencial.com/casas-reales/2026-01-17/ceremonia-irene-grecia-dentro-intimidad-fotos-lenguaje-corporal-felipe-letizia-sofia-leonor_4285827/", "date": "2026-01-17 17:01:00", "sentiment_score": 0.0683472529053688, "publisher": "elconfidencial"}, "8": {"title": "El Real Madrid en crisis y Kylian Mbappe\u0301 rompiendo re\u0301cords", "imgUrl": "https://i.ytimg.com/vi/6VC5VHn5EQM/mqdefault.jpg", "tags": ["lifestyle", "top"], "link": "https://meridiano.net/futbol/futbol-internacional/el-real-madrid-en-crisis-y-kylian-mbappe-rompiendo-records-202611712590", "date": "2026-01-17 17:00:00", "sentiment_score": 0.7849512249231339, "publisher": "meridiano"}, "9": {"title": "\u00bfPresidenta pa\u2019 cua\u0301ndo?: Hasta 2031 no habra\u0301 mujer al frente de Canarias", "imgUrl": "https://estaticos-cdn.prensaiberica.es/clip/2ffcdc8d-cc1e-4b4e-ada8-da83b3f0a150_16-9-aspect-ratio_default_0_x358y104.jpg", "tags": ["pol\u00edtica", "pp", "canarias", "psoe", "mujeres", "gobierno"], "link": "https://www.laprovincia.es/canarias/2026/01/17/presidenta-pa-2031-habra-mujer-125789959.html", "date": "2026-01-17 16:58:53", "sentiment_score": -0.36252689361572266, "publisher": "laprovincia"}, "10": {"title": "Madrid tendra\u0301 su propia Feria de Abril a lo grande: casetas, carruajes, famosos y moda flamenca", "imgUrl": "https://s1.ppllstatics.com/mujerhoy/www/multimedia/2026/01/16/feria-abril-sevilla-R3FoDsrhWfFI5LMH0HqNpWI-758x758@Mujer%20Hoy.jpg", "tags": ["gastronom\u00eda", "m\u00fasica"], "link": "https://www.mujerhoy.com/vivir/ocio/madrid-feria-abril-sevilla-casetas-famosos-musica-gastronomia-20260117000310-nt.html", "date": "2026-01-17 16:56:02", "sentiment_score": 0.10196113586425781, "publisher": "mujerhoy"}, "11": {"title": "Bob Pop opta a la Alcaldi\u0301a de Barcelona \"sin hada madrina\" y apelando al ADN de BComu\u0301", "imgUrl": "https://imagenes.heraldo.es/files/image_1920_1080/uploads/imagenes/2026/01/17/bob-pop-presenta-en-barcelona-su-candidatura-a-las-primarias-de-bcomu.jpeg", "tags": ["nacional"], "link": "https://www.heraldo.es/noticias/nacional/2026/01/17/bob-pop-opta-alcaldia-barcelona-sin-hada-madrina-apelando-adn-bcomu-1886438.html", "date": "2026-01-17 17:15:34", "sentiment_score": 0.4176337867975235, "publisher": "heraldo"}, "12": {"title": "No hace falta viajar 10.000 km para ver Japo\u0301n: Este barrio recrea la cultura japonesa con restaurantes y tiendas", "imgUrl": "https://s3.elespanol.com/2026/01/12/actualidad/1003744086813_260880157_1706x960.jpg", "tags": ["espa\u00f1a", "destinos", "viajes", "jap\u00f3n"], "link": "https://www.elespanol.com/viajes/20260117/no-hace-falta-viajar-km-ver-japon-barrio-recrea-cultura-japonesa-restaurantes-tiendas/1003744086806_0.html", "date": "2026-01-17 17:15:09", "sentiment_score": 0.5301325283944607, "publisher": "elespanol"}, "13": {"title": "Director de orquesta Zubin Mehta cancela sus conciertos en Israel en protesta a Netanyahu", "imgUrl": "https://www.infobae.com/assets/images/logos/fallback-promo-image-1200x630.png", "tags": ["efe"], "link": "https://www.infobae.com/america/agencias/2026/01/17/director-de-orquesta-zubin-mehta-cancela-sus-conciertos-en-israel-en-protesta-a-netanyahu/", "date": "2026-01-17 17:06:29", "sentiment_score": -0.853781757876277, "publisher": "infobae"}, "14": {"title": "Trump anuncia aranceles adicionales del 10% en ocho pai\u0301ses europeos", "imgUrl": "https://static1.ara.cat/clip/9d8411fe-3dce-4b91-9144-d1919d36f704_16-9-aspect-ratio_default_0.jpg", "tags": ["trump", "paises", "adicionales", "25", "europeos", "anuncia", "ocho", "aranceles"], "link": "https://es.ara.cat/internacional/europa/trump-anuncia-aranceles-adicionales-25-ocho-paises-europeos_1_5620888.html", "date": "2026-01-17 17:01:06", "sentiment_score": -0.24649813771247864, "publisher": "ara"}, "15": {"title": "Illa, \u00aben buen estado\u00bb tras una indisposicio\u0301n haciendo deporte aunque se somete a pruebas", "imgUrl": "https://i0.wp.com/cronicadecantabria.com/cr/wp-content/uploads/2026/01/20260117172703.jpg?fit=1920%2C1280&ssl=1", "tags": ["pol\u00edtica"], "link": "https://cronicadecantabria.com/cr/illa-en-buen-estado-tras-una-indisposicin-haciendo-deporte-aunque-se-somete-a-pruebas/", "date": "2026-01-17 17:00:04", "sentiment_score": -0.42838938534259796, "publisher": "cronicadecantabria"}, "16": {"title": "211 CV, hi\u0301brido, y desde 19.990 \u20ac con descuento, para esta oferta del EBRO s400", "imgUrl": "https://cdn.motor1.com/images/mgl/lElYlO/s3/ebro-s400-hibrido-2026.jpg", "tags": ["ebro s400", "suv", "suv/todoterreno", "ofertas", "coche chino"], "link": "https://es.motor1.com/news/784495/comprar-suv-eco-barato-precio-ebro-s400-19900euros/", "date": "2026-01-17 17:00:01", "sentiment_score": 0.5556455664336681, "publisher": "motor1"}, "17": {"title": "Arbeloa tras los pitos: \u00abFlorentino es el hombre ma\u0301s importante del club tras Santiago Bernabe\u0301u\u00bb", "imgUrl": "https://www.eldiarioalerta.com/media/diarioalerta/images/2026/01/17/2026011717483049374.jpg", "tags": ["f\u00fatbol"], "link": "https://www.eldiarioalerta.com/articulo/futbol/arbeloa-pitos-que-van-florentino-es-hombre-mas-importante-club-santiago-bernabeu/20260117175455578544.html", "date": "2026-01-17 16:54:55", "sentiment_score": 0.17603075504302979, "publisher": "eldiarioalerta"}, "18": {"title": "Seis an\u0303os sin juicios penales en Vic: \"Muchos abogados han tenido que hacer de taxistas hasta Manresa\"", "imgUrl": "https://static1.ara.cat/clip/2a56a2f7-b70e-4399-90d8-ad5538eddb34_16-9-aspect-ratio_default_0.jpg", "tags": ["abogados", "han", "tenido", "manresa", "juicios", "anos", "seis", "taxistas", "vic", "penales"], "link": "https://es.ara.cat/sociedad/justicia/seis-anos-juicios-penales-vic-abogados-han-tenido-taxistas-manresa_1_5620855.html", "date": "2026-01-17 16:52:07", "sentiment_score": -0.4238804429769516, "publisher": "ara"}, "19": {"title": "Mapa de los asesinatos por encargo en Espan\u0303a: de Madrid a Barcelona y Marbella", "imgUrl": "https://estaticos-cdn.prensaiberica.es/clip/da2327c0-5515-4f0d-b28c-38ccb0ee9dd1_16-9-aspect-ratio_default_0.jpg", "tags": ["narcotr\u00e1fico,asesinatos,barcelona,madrid,valencia,alicante,m\u00e1laga,guadalquivir,c\u00e1diz,sucesos"], "link": "https://www.elcorreoweb.es/sociedad/2026/01/17/mapa-sicarios-asesinatos-por-encargo-madrid-barcelona-valencia-alicante-cadiz-guadalquivir-125780776.html", "date": "2026-01-17 16:48:45", "sentiment_score": -0.9059211565181613, "publisher": "elcorreoweb_es"}, "20": {"title": "Illa, \"en buen estado\" tras una indisposicio\u0301n haciendo deporte aunque se somete a pruebas", "imgUrl": "https://www.infobae.com/resizer/v2/ZQADJVQXYNHARC36JDOAANRUBI.jpg?auth=0b6eba15d364ab003e790339a4684e4d3632c71b1a3ea20621d7c0b294fe0ec5&height=1280&smart=true&width=1920", "tags": ["europapress"], "link": "https://www.infobae.com/espana/agencias/2026/01/17/illa-en-buen-estado-tras-una-indisposicion-haciendo-deporte-aunque-se-somete-a-pruebas/", "date": "2026-01-17 16:46:10", "sentiment_score": -0.07115057110786438, "publisher": "infobae"}}