{"1": {"title": "El campeo\u0301n de Europa", "imgUrl": "https://estaticosgn-cdn.deia.eus/clip/ffda81bd-e861-4913-8e9c-98537c8a5096_16-9-aspect-ratio_default_0.jpg", "tags": ["europa", "monje", "champions", "campeon", "psg"], "link": "https://www.deia.eus/opinion/minuto-y-resultado/2025/12/10/campeon-europa-champions-monje-psg-10452078.html", "date": "2025-12-10 06:30:28", "sentiment_score": 0.4255000501871109, "publisher": "deia"}, "2": {"title": "Li\u0301o con los horarios de la Copa del Rey: el Atle\u0301tico jugara\u0301 un jueves a las 21 horas... y en Liga el domingo a las 14h", "imgUrl": "https://imagenes.20minutos.es/files/image_1920_1080/uploads/imagenes/2025/10/03/68dfa2ddae0aa.jpeg", "tags": ["f\u00fatbol"], "link": "https://www.20minutos.es/deportes/futbol/lio-con-los-horarios-copa-rey-atletico-jugara-un-jueves-las-21-horas-liga-domingo-las-14h_6908490_0.html", "date": "2025-12-10 06:22:30", "sentiment_score": -0.3678089492022991, "publisher": "minutos20"}, "3": {"title": "Una 'final' para un Xabi Alonso contra las cuerdas... con Guardiola amenazando: el Real Madrid se mide al Manchester City", "imgUrl": "https://imagenes.20minutos.es/files/image_1920_1080/uploads/imagenes/2025/12/09/6937c7ce95e753-47739676.jpeg", "tags": ["deportes"], "link": "https://www.20minutos.es/deportes/una-final-para-un-xabi-alonso-contra-las-cuerdas-con-guardiola-amenazando-real-madrid-se-mide-manchester-city_6908485_0.html", "date": "2025-12-10 06:22:13", "sentiment_score": -0.8521092459559441, "publisher": "minutos20"}, "4": {"title": "Cuando un partido cumbre parece imposible de coronar", "imgUrl": "https://estaticosgn-cdn.deia.eus/clip/ac05c947-9f1d-4345-b074-4d69786ff4ca_16-9-aspect-ratio_default_0.jpg", "tags": ["champions", "bilbao", "previa", "san mames", "psg"], "link": "https://www.deia.eus/athletic/2025/12/10/psg-san-mames-bilbao-previa-champions-10452065.html", "date": "2025-12-10 06:15:47", "sentiment_score": 0.5626818388700485, "publisher": "deia"}, "5": {"title": "\u00abNuestro objetivo es que el talento encuentre en Castilla y Leo\u0301n un ecosistema atractivo para desarrollarse\u00bb", "imgUrl": "https://s2.ppllstatics.com/elnortedecastilla/www/multimedia/2025/12/09/consejeraEducacion-kXKE-U240501263141uP-758x531@El%20Norte.jpg", "tags": ["junta de castilla y le\u00f3n", "castilla y le\u00f3n", "roc\u00edo lucas navas", "educaci\u00f3n", "innovaci\u00f3n", "universidades"], "link": "https://www.elnortedecastilla.es/castillayleon/objetivo-talento-encuentre-castilla-leon-ecosistema-atractivo-20251210065839-nt.html", "date": "2025-12-10 05:58:39", "sentiment_score": -0.03935988247394562, "publisher": "elnortedecastilla"}, "6": {"title": "Pedro Benito, el capita\u0301n precoz que lidera al Real Murcia", "imgUrl": "https://imagenes.lavozdealmeria.com/files/og_thumbnail/uploads/2025/12/10/693908f815e2c.jpeg", "tags": ["ud almer\u00eda"], "link": "https://www.lavozdealmeria.com/ud-almeria/409438/pedro-benito-capitan-precoz-lidera-real-murcia.html", "date": "2025-12-10 05:56:16", "sentiment_score": 0.09261927008628845, "publisher": "lavozdealmeria"}, "7": {"title": "Ana Boyer y Fernando Verdasco nos anuncian que esperan su cuarto hijo: \"Es un bebe\u0301 totalmente buscado\"", "imgUrl": "https://www.hola.com/horizon/landscape/11fa1ec25c60-dsc04623cut.jpg?im=Resize%3D%281200%29", "tags": ["actualidad", "contenido sensible", "ana boyer", "fernando verdasco", "\u00a1hola! +"], "link": "https://www.hola.com/actualidad/20251210871801/ana-boyer-fernando-verdasco-anuncian-esperan-cuarto-hijo-bebe-totalmente-buscado/", "date": "2025-12-10 05:06:00", "sentiment_score": 0.015072807669639587, "publisher": "hola"}, "8": {"title": "Pellegrini: \u00ab\u00bfEl Real Murcia anda bien?\u00bb", "imgUrl": "https://estaticos-cdn.prensaiberica.es/clip/f2e46585-c773-4cf2-b780-80c7128e5722_16-9-aspect-ratio_default_0_x834y773.jpg", "tags": ["real murcia", "betis", "nueva condomina", "deportes", "futbolistas"], "link": "https://www.laopiniondemurcia.es/deportes/2025/12/10/pellegrini-real-murcia-anda-124615843.html", "date": "2025-12-10 05:01:29", "sentiment_score": -0.16192619502544403, "publisher": "laopiniondemucria"}, "9": {"title": "El UCAM Murcia inicia en el Top 16 de la FIBA Europe Cup veinte di\u0301as sin tregua", "imgUrl": "https://estaticos-cdn.prensaiberica.es/clip/edd985a9-60d0-4abf-97c3-e41cf93ad4c0_16-9-aspect-ratio_default_0.jpg", "tags": ["ronda", "ucam", "real madrid", "ucam murcia cb", "joventut"], "link": "https://www.laopiniondemurcia.es/deportes/2025/12/10/ucam-murcia-inicia-top-16-124615358.html", "date": "2025-12-10 05:01:23", "sentiment_score": 0.21637046337127686, "publisher": "laopiniondemucria"}, "10": {"title": "Un deporte de he\u0301roes y villanos", "imgUrl": "https://estaticos-cdn.prensaiberica.es/clip/fdc9f9dd-a91f-4f8e-84ae-42549fc4f1bd_16-9-aspect-ratio_default_0.jpg", "tags": ["f\u00fatbol", "real madrid", "crisis"], "link": "https://www.elperiodicoextremadura.com/opinion/2025/12/10/deporte-heroes-villanos-124614767.html", "date": "2025-12-10 05:01:20", "sentiment_score": -0.705074205994606, "publisher": "elperiodicoextremadura"}, "11": {"title": "Ca l'Estevet: el restaurante que demuestra que la cocina catalana esta\u0301 estupendamente", "imgUrl": "https://static1.ara.cat/clip/72aa8d56-017a-4548-9473-e486ac2795a7_16-9-aspect-ratio_default_0_x1728y510.jpg", "tags": ["cocina", "estevet", "ca", "restaurante", "estupendamente", "demuestra", "catalana", "l"], "link": "https://es.ara.cat/comer/ca-l-estevet-restaurante-demuestra-cocina-catalana-estupendamente_1_5587701.html", "date": "2025-12-10 06:40:21", "sentiment_score": -0.20357392728328705, "publisher": "ara"}, "12": {"title": "Catalun\u0303a encara un di\u0301a de ambiente estable y alguna nevada de\u0301bil en el Pirineo occidental", "imgUrl": "https://a2.elespanol.com/cronicaglobal/2025/12/10/vida/1003742714785_15496590_1706x960.jpg", "tags": ["el tiempo", "meteorolog\u00eda", "meteocat", "los pirineos", "tiempo", "catalu\u00f1a", "nieve"], "link": "https://cronicaglobal.elespanol.com/el-tiempo/20251210/cataluna-encara-ambiente-estable-alguna-pirineo-occidental/1003742714783_0.html", "date": "2025-12-10 06:33:57", "sentiment_score": -0.7979859188199043, "publisher": "cronicaglobal_elespanol"}, "13": {"title": "Lo que debes saber hoy, 10 de diciembre, de Barcelona", "imgUrl": "https://a2.elespanol.com/metropoliabierta/2023/04/18/vivir-en-barcelona/757184282_9128786_1706x960.jpg", "tags": ["transports metropolitans barcelona tmb", "tr\u00e1fico", "vivir en barcelona", "clima", "transporte", "tiempo", "coches"], "link": "https://metropoliabierta.elespanol.com/vivir-en-barcelona/20251210/debes-saber-hoy-diciembre-barcelona/1003742714784_0.html", "date": "2025-12-10 06:32:11", "sentiment_score": 0.027752280235290527, "publisher": "metropoliabierta_elespanol"}, "14": {"title": "Li\u0301o con los horarios de la Copa del Rey: el Atle\u0301tico jugara\u0301 un jueves a las 21 horas... y en Liga el domingo a las 14h", "imgUrl": "https://imagenes.20minutos.es/files/image_1920_1080/uploads/imagenes/2025/10/03/68dfa2ddae0aa.jpeg", "tags": ["f\u00fatbol"], "link": "https://www.20minutos.es/deportes/futbol/lio-con-los-horarios-copa-rey-atletico-jugara-un-jueves-las-21-horas-liga-domingo-las-14h_6908490_0.html", "date": "2025-12-10 06:22:30", "sentiment_score": -0.3678089492022991, "publisher": "minutos20"}, "15": {"title": "Los motivos por los que Rosali\u0301a no hace estadios con su 'LUX Tour', una gira mundial con entradas agotadas en minutos", "imgUrl": "https://album.mediaset.es/eimg/2025/12/09/rosalia_76a8.jpg", "tags": ["cultura"], "link": "https://www.telecinco.es/noticias/cultura/20251210/motivos-rosalia-no-hace-estadios-lux-tour-entradas-agotadas_18_017801989.html", "date": "2025-12-10 06:15:55", "sentiment_score": 0.06084220111370087, "publisher": "telecinco_es"}, "16": {"title": "\"Mi padre me ensen\u0303o\u0301 dos cosas fundamentales: a cazar ya no ser obediente\"", "imgUrl": "https://static1.ara.cat/clip/ab8498aa-f935-4894-a447-783a6c4ac49b_16-9-aspect-ratio_default_0.jpg", "tags": ["no", "cosas", "padre", "cazar", "fundamentales", "obediente", "enseno"], "link": "https://es.ara.cat/cultura/leer/padre-enseno-cosas-fundamentales-cazar-no-obediente_128_5587693.html", "date": "2025-12-10 06:15:10", "sentiment_score": -0.13137187063694, "publisher": "ara"}, "17": {"title": "Muere el mu\u0301sico Robe Iniesta, li\u0301der de Extremoduro, a los 63 an\u0303os", "imgUrl": "https://static1.ara.cat/clip/e025f28d-779f-4d6a-9aa3-48ca939bee3e_16-9-aspect-ratio_default_0_x1511y0.jpg", "tags": ["musico", "iniesta", "muere", "63", "anos", "robe"], "link": "https://es.ara.cat/cultura/musica/muere-musico-robe-iniesta-63-anos_1_5587674.html", "date": "2025-12-10 06:00:58", "sentiment_score": -0.1320675164461136, "publisher": "ara"}, "18": {"title": "Una empresa aragonesa de venta de carne de jabali\u0301: \"Llevamos an\u0303os pagando la psicosis de la peste porcina; me recuerda a las vacas locas\"", "imgUrl": "https://estaticos-cdn.prensaiberica.es/clip/352d2bdb-53c7-417c-93db-b1be98b95c72_16-9-aspect-ratio_default_0.jpg", "tags": ["arag\u00f3n", "peste porcina", "dga"], "link": "https://www.elperiodicodearagon.com/aragon/2025/12/10/empresa-aragonesa-venta-carne-jabali-124606001.html", "date": "2025-12-10 06:00:29", "sentiment_score": -0.6539629325270653, "publisher": "elperiodicodearagon"}, "19": {"title": "El Gran Wyoming: \"La Justicia me ha citado dos veces solo para que me hicieran la foto\"", "imgUrl": "https://www.elplural.com/uploads/s1/21/07/98/4/el-gran-wyoming-en-los-premios-ondas-cadena-ser-x_7_480x270.jpeg", "tags": ["extratele"], "link": "https://www.elplural.com/extratele/gran-wyoming-justicia-me-ha-citado-dos-veces-solo-me-hicieran-foto_367025102", "date": "2025-12-10 06:00:11", "sentiment_score": -0.17718030512332916, "publisher": "elplural"}, "20": {"title": "Ruta literaria en Barcelona: recorrer la ciudad tras los pasos de Ruiz Zafo\u0301n", "imgUrl": "https://www.lavanguardia.com/files/og_thumbnail/files/fp/uploads/2025/12/09/6937fdbf27239.r_d.3028-2693-748.jpeg", "tags": ["viajes"], "link": "https://www.lavanguardia.com/magazine/viajes/20251210/11328468/ruta-literaria-barcelona-la-sombra-del-viento-ruiz-zafon.html", "date": "2025-12-10 06:00:00", "sentiment_score": 0.438973693177104, "publisher": "lavanguardia"}}